topsis/__init__.py
topsis/__main__.py
Topsis_Kirtan_102203600-1.0.0.dist-info/LICENCE
Topsis_Kirtan_102203600-1.0.0.dist-info/METADATA
Topsis_Kirtan_102203600-1.0.0.dist-info/WHEEL
Topsis_Kirtan_102203600-1.0.0.dist-info/entry_points.txt
Topsis_Kirtan_102203600-1.0.0.dist-info/top_level.txt
Topsis_Kirtan_102203600-1.0.0.dist-info/RECORD
