Metadata-Version: 2.2
Name: Topsis-Kirtan-102203600
Version: 1.0.0
Summary: It Ranks the Models based on MCDM
Home-page: https://github.com/KirtanDwivedi/Topsis-Kirtan-102203600
Author: Kirtan Dwivedi
Author-email: kirtand02@gmail.com
License: MIT
Classifier: License :: OSI Approved :: MIT License
Classifier: Programming Language :: Python :: 3.6
Classifier: Programming Language :: Python :: 3.7
Classifier: Programming Language :: Python :: 3.8
Classifier: Programming Language :: Python :: 3.11
License-File: LICENCE
Dynamic: author
Dynamic: author-email
Dynamic: classifier
Dynamic: description
Dynamic: description-content-type
Dynamic: home-page
Dynamic: license
Dynamic: summary
